deep_thinking/__init__.py
deep_thinking/__main__.py
deep_thinking/server.py
deep_thinking/models/__init__.py
deep_thinking/models/config.py
deep_thinking/models/task.py
deep_thinking/models/template.py
deep_thinking/models/thinking_session.py
deep_thinking/models/thought.py
deep_thinking/storage/__init__.py
deep_thinking/storage/json_file_store.py
deep_thinking/storage/migration.py
deep_thinking/storage/storage_manager.py
deep_thinking/storage/task_list_store.py
deep_thinking/templates/__init__.py
deep_thinking/templates/analysis.json
deep_thinking/templates/decision_making.json
deep_thinking/templates/problem_solving.json
deep_thinking/tools/__init__.py
deep_thinking/tools/export.py
deep_thinking/tools/sequential_thinking.py
deep_thinking/tools/session_manager.py
deep_thinking/tools/task_manager.py
deep_thinking/tools/template.py
deep_thinking/tools/visualization.py
deep_thinking/transports/__init__.py
deep_thinking/transports/sse.py
deep_thinking/transports/stdio.py
deep_thinking/utils/__init__.py
deep_thinking/utils/formatters.py
deep_thinking/utils/logger.py
deep_thinking/utils/template_loader.py
deepthinking-0.2.3.dist-info/METADATA
deepthinking-0.2.3.dist-info/WHEEL
deepthinking-0.2.3.dist-info/entry_points.txt
deepthinking-0.2.3.dist-info/licenses/LICENSE
deepthinking-0.2.3.dist-info/RECORD
