Metadata-Version: 2.4
Name: DeepThinking
Version: 0.2.3
Summary: Advanced sequential thinking MCP server with session management, templates, and visualization
Project-URL: Homepage, https://github.com/GeerMrc/DeepThinking
Project-URL: Documentation, https://github.com/GeerMrc/DeepThinking#readme
Project-URL: Repository, https://github.com/GeerMrc/DeepThinking
Project-URL: Issues, https://github.com/GeerMrc/DeepThinking/issues
Author-email: Maric <maricgeer@gmail.com>
Maintainer-email: Maric <maricgeer@gmail.com>
License: MIT
License-File: LICENSE
Keywords: ai,anthropic,claude,deep-thinking,mcp,mcp-server,model-context-protocol,sequential-thinking,session-management,thinking,visualization
Classifier: Development Status :: 4 - Beta
Classifier: Intended Audience :: Developers
Classifier: Intended Audience :: Science/Research
Classifier: License :: OSI Approved :: MIT License
Classifier: Operating System :: OS Independent
Classifier: Programming Language :: Python :: 3
Classifier: Programming Language :: Python :: 3 :: Only
Classifier: Programming Language :: Python :: 3.10
Classifier: Programming Language :: Python :: 3.11
Classifier: Programming Language :: Python :: 3.12
Classifier: Topic :: Scientific/Engineering :: Artificial Intelligence
Classifier: Topic :: Software Development :: Libraries :: Python Modules
Classifier: Typing :: Typed
Requires-Python: >=3.10
Requires-Dist: aiohttp>=3.9.0
Requires-Dist: asyncio>=3.4.3; python_version < '3.11'
Requires-Dist: mcp[cli]>=0.9.0
Requires-Dist: pydantic>=2.0.0
Provides-Extra: dev
Requires-Dist: mypy>=1.7.0; extra == 'dev'
Requires-Dist: pytest-asyncio>=0.21.0; extra == 'dev'
Requires-Dist: pytest-cov>=4.1.0; extra == 'dev'
Requires-Dist: pytest>=7.4.0; extra == 'dev'
Requires-Dist: ruff>=0.1.0; extra == 'dev'
Requires-Dist: types-aiofiles>=23.2.0; extra == 'dev'
